flwr_datasets/__init__.py
flwr_datasets/common/__init__.py
flwr_datasets/common/telemetry.py
flwr_datasets/common/typing.py
flwr_datasets/common/version.py
flwr_datasets/federated_dataset.py
flwr_datasets/metrics/__init__.py
flwr_datasets/metrics/utils.py
flwr_datasets/partitioner/__init__.py
flwr_datasets/partitioner/dirichlet_partitioner.py
flwr_datasets/partitioner/distribution_partitioner.py
flwr_datasets/partitioner/exponential_partitioner.py
flwr_datasets/partitioner/grouped_natural_id_partitioner.py
flwr_datasets/partitioner/id_to_size_fnc_partitioner.py
flwr_datasets/partitioner/iid_partitioner.py
flwr_datasets/partitioner/inner_dirichlet_partitioner.py
flwr_datasets/partitioner/linear_partitioner.py
flwr_datasets/partitioner/natural_id_partitioner.py
flwr_datasets/partitioner/partitioner.py
flwr_datasets/partitioner/pathological_partitioner.py
flwr_datasets/partitioner/shard_partitioner.py
flwr_datasets/partitioner/size_partitioner.py
flwr_datasets/partitioner/square_partitioner.py
flwr_datasets/preprocessor/__init__.py
flwr_datasets/preprocessor/divider.py
flwr_datasets/preprocessor/merger.py
flwr_datasets/preprocessor/preprocessor.py
flwr_datasets/utils.py
flwr_datasets/visualization/__init__.py
flwr_datasets/visualization/bar_plot.py
flwr_datasets/visualization/comparison_label_distribution.py
flwr_datasets/visualization/constants.py
flwr_datasets/visualization/heatmap_plot.py
flwr_datasets/visualization/label_distribution.py
flwr_datasets/visualization/utils.py
flwr_datasets-0.4.0.dist-info/METADATA
flwr_datasets-0.4.0.dist-info/WHEEL
flwr_datasets-0.4.0.dist-info/RECORD
