Metadata-Version: 2.1
Name: flwr-datasets
Version: 0.4.0
Summary: Flower Datasets
Home-page: https://flower.ai
License: Apache-2.0
Keywords: flower,fl,federated learning,federated analytics,federated evaluation,machine learning,dataset
Author: The Flower Authors
Author-email: hello@flower.ai
Requires-Python: >=3.9,<4.0
Classifier: Development Status :: 4 - Beta
Classifier: Intended Audience :: Developers
Classifier: Intended Audience :: Science/Research
Classifier: License :: OSI Approved :: Apache Software License
Classifier: Operating System :: MacOS :: MacOS X
Classifier: Operating System :: POSIX :: Linux
Classifier: Programming Language :: Python
Classifier: Programming Language :: Python :: 3
Classifier: Programming Language :: Python :: 3.9
Classifier: Programming Language :: Python :: 3.10
Classifier: Programming Language :: Python :: 3.11
Classifier: Programming Language :: Python :: 3.12
Classifier: Programming Language :: Python :: 3 :: Only
Classifier: Programming Language :: Python :: Implementation :: CPython
Classifier: Topic :: Scientific/Engineering
Classifier: Topic :: Scientific/Engineering :: Artificial Intelligence
Classifier: Topic :: Scientific/Engineering :: Mathematics
Classifier: Topic :: Software Development
Classifier: Topic :: Software Development :: Libraries
Classifier: Topic :: Software Development :: Libraries :: Python Modules
Classifier: Typing :: Typed
Provides-Extra: audio
Provides-Extra: vision
Requires-Dist: datasets (>=2.14.6,<=3.1.0)
Requires-Dist: librosa (>=0.10.0.post2) ; extra == "audio"
Requires-Dist: matplotlib (>=3.7.5,<4.0.0)
Requires-Dist: numpy (>=1.21.0,<2.0.0)
Requires-Dist: pillow (>=6.2.1) ; extra == "vision"
Requires-Dist: pyarrow (==16.1.0)
Requires-Dist: seaborn (>=0.13.0,<0.14.0)
Requires-Dist: soundfile (>=0.12.1) ; extra == "audio"
Requires-Dist: tqdm (>=4.66.1,<5.0.0)
Project-URL: Documentation, https://flower.ai/docs/datasets
Project-URL: Repository, https://github.com/adap/flower
